{
    "name": "OntoPress\\Tests\\DashboardControllerTest",
    "line": 8,
    "short_desc": "",
    "long_desc": "",
    "hint": null,
    "tags": [

    ],
    "namespace": "OntoPress\\Tests",
    "file": "src\/OntoPress\/\/Tests\/Controller\/DashboardControllerTest.php",
    "relative_file": null,
    "hash": "df52f0188d5c84260ff9f4e5cfd4b5a81901037b",
    "parent": "OntoPress\\Libary\\OntoPressTestCase",
    "modifiers": "Stmt_Class",
    "is_trait": false,
    "is_interface": false,
    "aliases": {
        "DashboardController": "OntoPress\\Controller\\DashboardController",
        "OntoPressTestCase": "OntoPress\\Libary\\OntoPressTestCase"
    },
    "errors": [

    ],
    "interfaces": [

    ],
    "traits": [

    ],
    "properties": [

    ],
    "methods": {
        "testDashboardController": {
            "name": "testDashboardController",
            "line": 10,
            "short_desc": "",
            "long_desc": "",
            "hint": null,
            "hint_desc": null,
            "tags": [

            ],
            "modifiers": "1",
            "is_by_ref": "",
            "exceptions": [

            ],
            "errors": [

            ],
            "parameters": [

            ]
        }
    },
    "constants": [

    ]
}